LICENSE
README.md
setup.py
NlpToolkit_SemanticRoleLabeling.egg-info/PKG-INFO
NlpToolkit_SemanticRoleLabeling.egg-info/SOURCES.txt
NlpToolkit_SemanticRoleLabeling.egg-info/dependency_links.txt
NlpToolkit_SemanticRoleLabeling.egg-info/requires.txt
NlpToolkit_SemanticRoleLabeling.egg-info/top_level.txt
SemanticRoleLabeling/__init__.py
SemanticRoleLabeling/ParseTree/__init__.py
SemanticRoleLabeling/ParseTree/Propbank/AutoArgument.py
SemanticRoleLabeling/ParseTree/Propbank/__init__.py
SemanticRoleLabeling/Sentence/__init__.py
SemanticRoleLabeling/Sentence/FrameNet/SentenceAutoFramePredicate.py
SemanticRoleLabeling/Sentence/FrameNet/TurkishSentenceAutoFramePredicate.py
SemanticRoleLabeling/Sentence/FrameNet/__init__.py
SemanticRoleLabeling/Sentence/Propbank/SentenceAutoArgument.py
SemanticRoleLabeling/Sentence/Propbank/SentenceAutoPredicate.py
SemanticRoleLabeling/Sentence/Propbank/TurkishSentenceAutoArgument.py
SemanticRoleLabeling/Sentence/Propbank/TurkishSentenceAutoPredicate.py
SemanticRoleLabeling/Sentence/Propbank/__init__.py