Metadata-Version: 2.1
Name: NlpToolkit-SemanticRoleLabeling
Version: 1.0.3
Summary: Semantic Role Labeling Library
Home-page: https://github.com/StarlangSoftware/SemanticRoleLabeling-Py
Author: olcaytaner
Author-email: olcay.yildiz@ozyegin.edu.tr
License: UNKNOWN
Platform: UNKNOWN
License-File: LICENSE
